{
  "variables": {
    "66319": {
      "years": [
        2004,
        2004,
        2004,
        2004,
        2004,
        2005,
        2005,
        2005,
        2005,
        2005,
        2006,
        2006,
        2006,
        2006,
        2006,
        2006,
        2006,
        2006,
        2006,
        2006,
        2006,
        2007,
        2007,
        2007,
        2007,
        2007,
        2007,
        2007,
        2007,
        2007,
        2007,
        2007,
        2007,
        2007,
        2008,
        2008,
        2008,
        2008,
        2008,
        2008,
        2008,
        2008,
        2008,
        2008,
        2008,
        2008,
        2008,
        2009,
        2009,
        2009,
        2009,
        2009,
        2009,
        2009,
        2009,
        2009,
        2009,
        2009,
        2009,
        2009,
        2009,
        2009,
        2010,
        2010,
        2010,
        2010,
        2010,
        2010,
        2010,
        2010,
        2010,
        2010,
        2010,
        2010,
        2010,
        2010,
        2010,
        2011,
        2011,
        2011,
        2011,
        2011,
        2011,
        2011,
        2011,
        2011,
        2011,
        2011,
        2011,
        2011,
        2011,
        2011,
        2011,
        2012,
        2012,
        2012,
        2012,
        2012,
        2012,
        2012,
        2012,
        2012,
        2012,
        2012,
        2012,
        2012,
        2012,
        2013,
        2013,
        2013,
        2013,
        2013,
        2013,
        2013,
        2013,
        2014,
        2014,
        2014,
        2014
      ],
      "entities": [
        37,
        113,
        166,
        170,
        172,
        37,
        113,
        166,
        170,
        172,
        34,
        37,
        113,
        132,
        148,
        160,
        166,
        170,
        172,
        201,
        234,
        21,
        34,
        37,
        98,
        113,
        132,
        148,
        160,
        166,
        170,
        172,
        201,
        234,
        21,
        34,
        37,
        98,
        113,
        132,
        148,
        160,
        166,
        170,
        172,
        201,
        234,
        21,
        34,
        37,
        63,
        98,
        105,
        113,
        132,
        148,
        160,
        166,
        170,
        172,
        201,
        234,
        21,
        37,
        63,
        97,
        98,
        105,
        113,
        132,
        148,
        160,
        166,
        170,
        172,
        201,
        234,
        21,
        37,
        63,
        97,
        98,
        113,
        132,
        139,
        148,
        160,
        166,
        170,
        172,
        201,
        234,
        259,
        21,
        37,
        63,
        97,
        98,
        113,
        132,
        139,
        160,
        166,
        170,
        172,
        201,
        259,
        37,
        63,
        97,
        98,
        113,
        160,
        170,
        172,
        37,
        113,
        170,
        172
      ],
      "values": [
        4.3,
        11.6,
        6.8,
        14.2,
        4.7,
        6.8,
        12.9,
        5.7,
        17.9,
        4.7,
        16.5,
        6.2,
        13,
        28,
        15.1,
        54.8,
        6.3,
        15.2,
        4.5,
        5.8,
        19,
        -22.9,
        14.1,
        5.3,
        1.6,
        12.9,
        31.9,
        15.9,
        40.5,
        2.9,
        17.1,
        3.7,
        8.8,
        18.4,
        -39.9,
        10.2,
        4,
        1.1,
        12.3,
        26.7,
        10.6,
        36,
        12,
        16.2,
        2.7,
        4.1,
        3.8,
        -26.2,
        16.5,
        8.1,
        1.9,
        2.6,
        25.9,
        13.2,
        20.7,
        2.7,
        41,
        14.9,
        22.6,
        4.1,
        14.4,
        19.2,
        -19.1,
        5.8,
        1.6,
        4.6,
        1.8,
        15,
        12.6,
        31.4,
        7.5,
        26.2,
        14,
        17.3,
        2.6,
        3.9,
        22,
        -32.1,
        5.6,
        1.5,
        5.8,
        2.3,
        12.3,
        38.8,
        26.9,
        -4,
        11.8,
        12,
        17,
        2.7,
        4.1,
        -3.1,
        31.9,
        -18,
        3.6,
        1,
        5.3,
        2.6,
        11.7,
        33.3,
        19,
        5.3,
        16.1,
        21.1,
        3,
        7,
        24.1,
        3,
        1,
        3.7,
        1.8,
        10.9,
        13.5,
        18.9,
        3.4,
        4.4,
        13.3,
        16.6,
        3.1
      ],
      "id": 66319,
      "name": "Producer Support (IDB Agrimonitor)",
      "unit": "%",
      "description": "",
      "createdAt": "2018-01-16T10:37:15.000Z",
      "updatedAt": "2018-02-28T08:59:09.000Z",
      "code": null,
      "coverage": "Latin America",
      "timespan": "",
      "datasetId": 1901,
      "sourceId": 13910,
      "shortUnit": null,
      "display": {},
      "columnOrder": 0,
      "originalMetadata": null,
      "datasetName": "Agricultural policy support - (Agrimonitor, 2017)",
      "s_id": 13910,
      "s_name": "Agricultural policy support - (Inter-American Development Bank, Agrimonitor, 2017)",
      "source": {
        "id": 13910,
        "name": "Agricultural policy support - (Inter-American Development Bank, Agrimonitor, 2017)",
        "dataPublishedBy": "Inter-American Development Bank (IDB) Agrimonitor",
        "dataPublisherSource": "",
        "link": "https://data.iadb.org/",
        "retrievedData": "",
        "additionalInfo": "The IDB Agrimonitor defines these variables as the following.\n\nProducer Support (%): The annual monetary value of gross transfers from consumers and taxpayers to agricultural producers, measured at the farm-gate level, arising from policy measures that support agriculture, regardless of their nature, objectives or impacts on farm production or income.\n\nTotal Support (%): The annual monetary value of all gross transfers from taxpayers and consumers arising from policy measures that support agriculture, net of associated budgetary receipts, regardless of their objectives and impacts on farm production and income, or consumption of farm products.\n\nGeneral Support Services (%): The annual monetary value of gross transfers to general services provided to agricultural producers collectively (such as research, development, training, inspection, marketing and promotion), arising from policy measures that support agriculture regardless of their nature, objectives and impacts on farm production, income, or consumption. The GSSE does not include any transfers to individual producers.\n"
      }
    }
  },
  "entityKey": {
    "21": {
      "name": "Argentina",
      "code": "ARG"
    },
    "34": {
      "name": "Bolivia",
      "code": "BOL"
    },
    "37": {
      "name": "Brazil",
      "code": "BRA"
    },
    "63": {
      "name": "Uruguay",
      "code": "URY"
    },
    "97": {
      "name": "Peru",
      "code": "PER"
    },
    "98": {
      "name": "Paraguay",
      "code": "PRY"
    },
    "105": {
      "name": "Nicaragua",
      "code": "NIC"
    },
    "113": {
      "name": "Mexico",
      "code": "MEX"
    },
    "132": {
      "name": "Jamaica",
      "code": "JAM"
    },
    "139": {
      "name": "Honduras",
      "code": "HND"
    },
    "148": {
      "name": "Guatemala",
      "code": "GTM"
    },
    "160": {
      "name": "Dominican Republic",
      "code": "DOM"
    },
    "166": {
      "name": "Costa Rica",
      "code": "CRI"
    },
    "170": {
      "name": "Colombia",
      "code": "COL"
    },
    "172": {
      "name": "Chile",
      "code": "CHL"
    },
    "201": {
      "name": "Ecuador",
      "code": "ECU"
    },
    "234": {
      "name": "Suriname",
      "code": "SUR"
    },
    "259": {
      "name": "El Salvador",
      "code": "SLV"
    }
  }
}