{
  "id": 85924,
  "name": "Number of cigarettes smoked per smoker per day, males (ISS (2017))",
  "unit": "",
  "description": "",
  "createdAt": "2018-03-09T11:03:53.000Z",
  "updatedAt": "2023-06-15T05:05:42.000Z",
  "coverage": "",
  "timespan": "",
  "datasetId": 2465,
  "columnOrder": 0,
  "dataPath": "https://api.ourworldindata.org/v1/indicators/85924.data.json",
  "metadataPath": "https://api.ourworldindata.org/v1/indicators/85924.metadata.json",
  "datasetName": "Smoking cigarette sales (International Smoking Statistics (2017)) ",
  "type": "float",
  "nonRedistributable": false,
  "display": {},
  "source": {
    "id": 14668,
    "name": "International Smoking Statistics (2017)",
    "dataPublishedBy": "Authors Barbara Forey, Jan Hamling, John Hamling, Alison Thornton, Peter Lee",
    "dataPublisherSource": "National statistics",
    "link": "http://www.pnlee.co.uk/ISS.htm",
    "retrievedDate": "20/02/2018",
    "additionalInfo": "Total cigarettes include both manufactured and hand-rolled cigarettes. For Latvia, total cigarettes comprise of manufactured cigarettes and Papyrosi cigarettes. \n\nIn some countries the original data reports 0 for a specific year, with otherwise large reported values for the years before and after. In these cases we treat 0 as a mistake and report missing data for that year.\n\nThe 'number of cigarettes smoked per person per day' for both males and females has been averaged across all years in which multiple estimates were provided in the ISS dataset for the United States, to arrive at one estimate for each year.\n\nThe time series for Germany includes West Germany cigarette sales for the 1948-1989 period ."
  },
  "dimensions": {
    "years": {
      "values": [
        {
          "id": 1947
        },
        {
          "id": 1955
        },
        {
          "id": 1958
        },
        {
          "id": 1959
        },
        {
          "id": 1965
        },
        {
          "id": 1966
        },
        {
          "id": 1967
        },
        {
          "id": 1968
        },
        {
          "id": 1970
        },
        {
          "id": 1972
        },
        {
          "id": 1974
        },
        {
          "id": 1975
        },
        {
          "id": 1976
        },
        {
          "id": 1977
        },
        {
          "id": 1978
        },
        {
          "id": 1979
        },
        {
          "id": 1980
        },
        {
          "id": 1982
        },
        {
          "id": 1983
        },
        {
          "id": 1985
        },
        {
          "id": 1987
        },
        {
          "id": 1988
        },
        {
          "id": 1989
        },
        {
          "id": 1990
        },
        {
          "id": 1991
        },
        {
          "id": 1992
        },
        {
          "id": 1993
        },
        {
          "id": 1994
        },
        {
          "id": 1995
        },
        {
          "id": 1996
        },
        {
          "id": 1997
        },
        {
          "id": 1998
        },
        {
          "id": 1999
        },
        {
          "id": 2000
        },
        {
          "id": 2001
        },
        {
          "id": 2002
        },
        {
          "id": 2003
        },
        {
          "id": 2004
        },
        {
          "id": 2005
        },
        {
          "id": 2006
        },
        {
          "id": 2007
        },
        {
          "id": 2008
        },
        {
          "id": 2009
        },
        {
          "id": 2010
        },
        {
          "id": 2011
        },
        {
          "id": 2012
        },
        {
          "id": 2013
        },
        {
          "id": 2014
        }
      ]
    },
    "entities": {
      "values": [
        {
          "id": 13,
          "name": "United States",
          "code": "USA"
        }
      ]
    }
  }
}