{
  "id": 820781,
  "name": "Mean value - Water body category: lakes - Indicator: Total phosphorus - Unit: mg/L",
  "unit": "milligrams per litre",
  "createdAt": "2024-02-15T17:27:18.000Z",
  "updatedAt": "2024-09-30T16:35:38.000Z",
  "coverage": "",
  "timespan": "1992-2021",
  "datasetId": 6386,
  "shortUnit": "mg/L",
  "columnOrder": 0,
  "shortName": "meanvalue__water_body_category_lakes__indicator_total_phosphorus__unit_mg_l",
  "catalogPath": "grapher/wash/2024-01-04/nutrients/nutrients#meanvalue__water_body_category_lakes__indicator_total_phosphorus__unit_mg_l",
  "dimensions": {
    "years": {
      "values": [
        {
          "id": 2003
        },
        {
          "id": 2004
        },
        {
          "id": 2005
        },
        {
          "id": 2006
        },
        {
          "id": 2007
        },
        {
          "id": 2008
        },
        {
          "id": 2009
        },
        {
          "id": 2010
        },
        {
          "id": 2011
        },
        {
          "id": 2012
        },
        {
          "id": 2013
        },
        {
          "id": 2014
        },
        {
          "id": 2015
        },
        {
          "id": 2016
        },
        {
          "id": 2017
        },
        {
          "id": 2018
        },
        {
          "id": 2019
        },
        {
          "id": 2020
        },
        {
          "id": 2021
        },
        {
          "id": 1992
        },
        {
          "id": 1993
        },
        {
          "id": 1994
        },
        {
          "id": 1995
        },
        {
          "id": 1996
        },
        {
          "id": 1997
        },
        {
          "id": 1998
        },
        {
          "id": 1999
        },
        {
          "id": 2000
        },
        {
          "id": 2001
        },
        {
          "id": 2002
        }
      ]
    },
    "entities": {
      "values": [
        {
          "id": 16,
          "name": "Albania",
          "code": "ALB"
        },
        {
          "id": 24,
          "name": "Austria",
          "code": "AUT"
        },
        {
          "id": 4,
          "name": "Belgium",
          "code": "BEL"
        },
        {
          "id": 35,
          "name": "Bosnia and Herzegovina",
          "code": "BIH"
        },
        {
          "id": 39,
          "name": "Bulgaria",
          "code": "BGR"
        },
        {
          "id": 165,
          "name": "Croatia",
          "code": "HRV"
        },
        {
          "id": 163,
          "name": "Cyprus",
          "code": "CYP"
        },
        {
          "id": 162,
          "name": "Czechia",
          "code": "CZE"
        },
        {
          "id": 161,
          "name": "Denmark",
          "code": "DNK"
        },
        {
          "id": 156,
          "name": "Estonia",
          "code": "EST"
        },
        {
          "id": 369127,
          "name": "Europe (EEA)",
          "code": null
        },
        {
          "id": 155,
          "name": "Finland",
          "code": "FIN"
        },
        {
          "id": 3,
          "name": "France",
          "code": "FRA"
        },
        {
          "id": 6,
          "name": "Germany",
          "code": "DEU"
        },
        {
          "id": 149,
          "name": "Greece",
          "code": "GRC"
        },
        {
          "id": 138,
          "name": "Hungary",
          "code": "HUN"
        },
        {
          "id": 207,
          "name": "Iceland",
          "code": "ISL"
        },
        {
          "id": 2,
          "name": "Ireland",
          "code": "IRL"
        },
        {
          "id": 8,
          "name": "Italy",
          "code": "ITA"
        },
        {
          "id": 379,
          "name": "Kosovo",
          "code": "OWID_KOS"
        },
        {
          "id": 122,
          "name": "Latvia",
          "code": "LVA"
        },
        {
          "id": 119,
          "name": "Lithuania",
          "code": "LTU"
        },
        {
          "id": 212,
          "name": "Malta",
          "code": "MLT"
        },
        {
          "id": 215,
          "name": "Montenegro",
          "code": "MNE"
        },
        {
          "id": 5,
          "name": "Netherlands",
          "code": "NLD"
        },
        {
          "id": 66,
          "name": "North Macedonia",
          "code": "MKD"
        },
        {
          "id": 102,
          "name": "Norway",
          "code": "NOR"
        },
        {
          "id": 11,
          "name": "Poland",
          "code": "POL"
        },
        {
          "id": 95,
          "name": "Portugal",
          "code": "PRT"
        },
        {
          "id": 92,
          "name": "Romania",
          "code": "ROU"
        },
        {
          "id": 88,
          "name": "Serbia",
          "code": "SRB"
        },
        {
          "id": 85,
          "name": "Slovakia",
          "code": "SVK"
        },
        {
          "id": 83,
          "name": "Slovenia",
          "code": "SVN"
        },
        {
          "id": 9,
          "name": "Spain",
          "code": "ESP"
        },
        {
          "id": 10,
          "name": "Sweden",
          "code": "SWE"
        },
        {
          "id": 7,
          "name": "Switzerland",
          "code": "CHE"
        },
        {
          "id": 70,
          "name": "Turkey",
          "code": "TUR"
        }
      ]
    }
  },
  "descriptionShort": "Average annual concentration of total phosphorus in lakes.\n",
  "type": "float",
  "grapherConfigIdETL": "0191c16a-91af-76e7-a607-5c34bdf6b8e8",
  "dataChecksum": "cdad6ecb6b1696e998d4ed47d48cd529",
  "metadataChecksum": "a840913529e34cc4df8f2c9b753676aa",
  "datasetName": "Water Information System for Europe (WISE) statistics",
  "updatePeriodDays": 365,
  "datasetVersion": "2024-01-04",
  "nonRedistributable": false,
  "display": {
    "unit": "milligrams per litre",
    "shortUnit": "mg/L",
    "numDecimalPlaces": 2
  },
  "schemaVersion": 2,
  "processingLevel": "minor",
  "presentation": {
    "titlePublic": "Total phosphorus concentration in lakes\n",
    "topicTagsLinks": [
      "Clean Water",
      "Environmental Impacts of Food Production"
    ],
    "faqs": []
  },
  "descriptionKey": [],
  "origins": [
    {
      "id": 429,
      "titleSnapshot": "WISE statistics - Nutrients",
      "title": "Water Information System for Europe (WISE) statistics",
      "description": "The WISE Statistics are aggregated data products for creation of the Freshwater indicators \"Oxygen consuming substances in European rivers\" and \"Nutrients in Freshwater in Europe\", which are published at the EEA website.",
      "producer": "European Environment Agency",
      "citationFull": "European Environment Agency (2023). WISE statistics - nutrients (1990-2021), 2023.",
      "attributionShort": "EEA",
      "urlMain": "https://sdi.eea.europa.eu/catalogue/srv/eng/catalog.search#/metadata/271f545b-cdc7-4b18-89fb-1adda5a3f4ef",
      "urlDownload": "https://discodata.eea.europa.eu/download/WISE_Indicators/v4r1/AggregatedData_Country",
      "dateAccessed": "2024-01-04",
      "datePublished": "2023-07-14",
      "license": {
        "url": "https://www.eea.europa.eu/en/legal-notice#copyright-notice",
        "name": "CC BY 4.0"
      }
    },
    {
      "id": 430,
      "titleSnapshot": "WISE statistics - Nutrients - Europe",
      "title": "Water Information System for Europe (WISE) statistics",
      "description": "The WISE Statistics are aggregated data products for creation of the Freshwater indicators \"Oxygen consuming substances in European rivers\" and \"Nutrients in Freshwater in Europe\", which are published at the EEA website.",
      "producer": "European Environment Agency",
      "citationFull": "European Environment Agency (2023). WISE statistics - nutrients (1990-2021), 2023.",
      "attributionShort": "EEA",
      "urlMain": "https://discomap.eea.europa.eu/App/DiscodataViewer/?fqn=[WISE_Indicators].[v4r1].[AggregatedData_Europe]",
      "dateAccessed": "2024-02-15",
      "datePublished": "2023-07-14",
      "license": {
        "url": "https://www.eea.europa.eu/en/legal-notice#copyright-notice",
        "name": "CC BY 4.0"
      }
    }
  ]
}