{
  "id": 576767,
  "name": "Agree \"Most people would try to take advantage of you\"",
  "unit": "%",
  "description": "% of respondents replying that people \"would take advantage\" when asked \"Do you think most people try to take advantage of you\". Possible answers include they \"would try to be fair\", \"would take advantage\" and \"do not know\".",
  "createdAt": "2023-03-08T18:44:35.000Z",
  "updatedAt": "2023-03-13T18:22:28.000Z",
  "coverage": "",
  "timespan": "2004-2014",
  "datasetId": 5914,
  "shortUnit": "%",
  "columnOrder": 0,
  "shortName": "take_advantage",
  "catalogPath": "grapher/wvs/2023-03-08/wvs_trust/wvs_trust",
  "dataPath": "https://catalog.ourworldindata.org/baked-variables/live_grapher/data/576767.json",
  "metadataPath": "https://catalog.ourworldindata.org/baked-variables/live_grapher/metadata/576767.json",
  "datasetName": "Trust questions in the World Values Survey Dataset (WVS, 2022)",
  "type": "float",
  "nonRedistributable": false,
  "display": {
    "name": "Agree \"Most people would try to take advantage of you\"",
    "unit": "%",
    "shortUnit": "%",
    "numDecimalPlaces": 1
  },
  "source": {
    "id": 27432,
    "name": "World Values Survey (2022)",
    "dataPublishedBy": "Inglehart, R., C. Haerpfer, A. Moreno, C. Welzel, K. Kizilova, J. Diez-Medrano, M. Lagos, P. Norris, E. Ponarin & B. Puranen (eds.). 2022. World Values Survey: All Rounds - Country-Pooled Datafile. Madrid, Spain & Vienna, Austria: JD Systems Institute & WVSA Secretariat. Dataset Version 4.0. doi:10.14281/18241.17",
    "dataPublisherSource": "",
    "link": "https://www.worldvaluessurvey.org/WVSDocumentationWVL.jsp",
    "retrievedDate": "2023-03-08",
    "additionalInfo": "The World Values Survey (WVS) is an international research program devoted to the scientific and academic study of social, political, economic, religious and cultural values of people in the world. The main research instrument of the project is a representative comparative social survey conducted globally every five years.\n\nIn the Our World in Data dataset we calculate national totals for the following questions:\n<ul>\n  <li>Generally speaking, would you say that most people can be trusted or that you need to be very careful in dealing with people?</li>\n  <li>Could you tell me whether you trust people from you meet for the first time completely, somewhat, not very much or not at all?</li>\n  <li>Could you tell me whether you trust people you know personally completely, somewhat, not very much or not at all?</li>\n  <li>Could you tell me how much confidence you have in the government? Is it a great deal of confidence, quite a lot of confidence, not very much confidence or none at all?</li>\n  <li>Do you think most people try to take advantage of you?</li>\n</ul>\n\nThe WVS runs a new survey wave every five years; the last update was done in 2022.  We will aim to update our data on Our World in Data soon after the WVS updates the source data with a new wave. You can access the source page at the link above and see the latest available data from the WVS.\n"
  },
  "dimensions": {
    "years": {
      "values": [
        {
          "id": 2004
        },
        {
          "id": 2014
        }
      ]
    },
    "entities": {
      "values": [
        {
          "id": 16,
          "name": "Albania",
          "code": "ALB"
        },
        {
          "id": 17,
          "name": "Algeria",
          "code": "DZA"
        },
        {
          "id": 21,
          "name": "Argentina",
          "code": "ARG"
        },
        {
          "id": 28,
          "name": "Bangladesh",
          "code": "BGD"
        },
        {
          "id": 35,
          "name": "Bosnia and Herzegovina",
          "code": "BIH"
        },
        {
          "id": 44,
          "name": "Canada",
          "code": "CAN"
        },
        {
          "id": 172,
          "name": "Chile",
          "code": "CHL"
        },
        {
          "id": 171,
          "name": "China",
          "code": "CHN"
        },
        {
          "id": 65,
          "name": "Egypt",
          "code": "EGY"
        },
        {
          "id": 137,
          "name": "India",
          "code": "IND"
        },
        {
          "id": 136,
          "name": "Indonesia",
          "code": "IDN"
        },
        {
          "id": 135,
          "name": "Iran",
          "code": "IRN"
        },
        {
          "id": 134,
          "name": "Iraq",
          "code": "IRQ"
        },
        {
          "id": 14,
          "name": "Japan",
          "code": "JPN"
        },
        {
          "id": 130,
          "name": "Jordan",
          "code": "JOR"
        },
        {
          "id": 126,
          "name": "Kyrgyzstan",
          "code": "KGZ"
        },
        {
          "id": 113,
          "name": "Mexico",
          "code": "MEX"
        },
        {
          "id": 111,
          "name": "Moldova",
          "code": "MDA"
        },
        {
          "id": 215,
          "name": "Montenegro",
          "code": "MNE"
        },
        {
          "id": 110,
          "name": "Morocco",
          "code": "MAR"
        },
        {
          "id": 106,
          "name": "New Zealand",
          "code": "NZL"
        },
        {
          "id": 103,
          "name": "Nigeria",
          "code": "NGA"
        },
        {
          "id": 66,
          "name": "North Macedonia",
          "code": "MKD"
        },
        {
          "id": 101,
          "name": "Pakistan",
          "code": "PAK"
        },
        {
          "id": 97,
          "name": "Peru",
          "code": "PER"
        },
        {
          "id": 96,
          "name": "Philippines",
          "code": "PHL"
        },
        {
          "id": 93,
          "name": "Puerto Rico",
          "code": "PRI"
        },
        {
          "id": 90,
          "name": "Saudi Arabia",
          "code": "SAU"
        },
        {
          "id": 88,
          "name": "Serbia",
          "code": "SRB"
        },
        {
          "id": 86,
          "name": "Singapore",
          "code": "SGP"
        },
        {
          "id": 81,
          "name": "South Africa",
          "code": "ZAF"
        },
        {
          "id": 127,
          "name": "South Korea",
          "code": "KOR"
        },
        {
          "id": 9,
          "name": "Spain",
          "code": "ESP"
        },
        {
          "id": 10,
          "name": "Sweden",
          "code": "SWE"
        },
        {
          "id": 64,
          "name": "Tanzania",
          "code": "TZA"
        },
        {
          "id": 70,
          "name": "Turkey",
          "code": "TUR"
        },
        {
          "id": 68,
          "name": "Uganda",
          "code": "UGA"
        },
        {
          "id": 13,
          "name": "United States",
          "code": "USA"
        },
        {
          "id": 238,
          "name": "Venezuela",
          "code": "VEN"
        },
        {
          "id": 84,
          "name": "Vietnam",
          "code": "VNM"
        },
        {
          "id": 80,
          "name": "Zimbabwe",
          "code": "ZWE"
        }
      ]
    }
  }
}