{
  "id": 997271,
  "name": "Antimicrobial quantities adjusted for animal biomass (non-adjusted for reporting coverage)",
  "unit": "milligrams per kilogram",
  "createdAt": "2024-10-29T12:11:51.000Z",
  "updatedAt": "2024-10-29T12:11:51.000Z",
  "coverage": "",
  "timespan": "2014-2021",
  "datasetId": 6769,
  "shortUnit": "mg/kg",
  "columnOrder": 0,
  "shortName": "mg_per_kg_non_adjusted",
  "catalogPath": "grapher/antibiotics/2024-10-23/animuse_year/animuse_year#mg_per_kg_non_adjusted",
  "descriptionShort": "[Antimicrobial](#dod:antimicrobial) use is measured in milligrams per kilogram of meat product. Not all countries report on their antimicrobial use, these estimates do not account for for gaps in data coverage.",
  "type": "float",
  "datasetName": "ANIMUSE",
  "updatePeriodDays": 365,
  "datasetVersion": "2024-10-23",
  "nonRedistributable": false,
  "display": {
    "unit": "milligrams per kilogram",
    "shortUnit": "mg/kg"
  },
  "schemaVersion": 2,
  "presentation": {
    "topicTagsLinks": [
      "Global Health",
      "Antibiotics"
    ],
    "faqs": []
  },
  "descriptionKey": [],
  "dimensions": {
    "years": {
      "values": [
        {
          "id": 2014
        },
        {
          "id": 2015
        },
        {
          "id": 2016
        },
        {
          "id": 2017
        },
        {
          "id": 2018
        },
        {
          "id": 2019
        },
        {
          "id": 2020
        },
        {
          "id": 2021
        }
      ]
    },
    "entities": {
      "values": [
        {
          "id": 370638,
          "name": "Africa (WOAH)",
          "code": null
        },
        {
          "id": 370636,
          "name": "Americas (WOAH)",
          "code": null
        },
        {
          "id": 370637,
          "name": "Asia (WOAH)",
          "code": null
        },
        {
          "id": 370639,
          "name": "Europe (WOAH)",
          "code": null
        },
        {
          "id": 355,
          "name": "World",
          "code": "OWID_WRL"
        }
      ]
    }
  },
  "origins": [
    {
      "id": 1905,
      "titleSnapshot": "ANIMUSE - Year Analysis",
      "title": "ANIMUSE",
      "description": "The World Organisation for Animal Health (WOAH) has been collecting data on the amounts and reasons for antimicrobial use in animals since 2015. This information is an essential asset to reduce the overuse and misuse of medication and to curb the spread of antimicrobial resistance (AMR). ANIMUSE, the global database on ANImal antiMicrobial USE, facilitates access to this crucial and growing set of information.\n\nAntimicrobials are naturally occurring, semi-synthetic or synthetic substance that exhibits antimicrobial activity (kill or inhibit the growth of micro-organisms) at concentrations attainable in vivo. Anthelmintics and substances classed as disinfectants or antiseptics are excluded from this definition.",
      "producer": "World Organisation for Animal Health",
      "citationFull": "ANIMUSE Interactive Report (2024), World Organisation for Animal Health.",
      "attributionShort": "WOAH",
      "urlMain": "https://amu.woah.org/amu-system-portal/home",
      "dateAccessed": "2024-10-23",
      "datePublished": "2022-09-01",
      "license": {
        "url": "https://amu.woah.org/amu-system-portal/cms/view/bef2f483-36e3-4671-a791-ace982958c7d/846dd494-0007-4d31-aa80-fb61273d9c06/public",
        "name": "CC BY 4.0"
      }
    }
  ]
}