{
  "id": 147557,
  "name": "Maize yield climate impact (%)",
  "unit": "",
  "createdAt": "2021-07-09T09:12:11.000Z",
  "updatedAt": "2023-02-17T10:06:44.000Z",
  "coverage": "",
  "timespan": "",
  "datasetId": 5344,
  "columnOrder": 0,
  "dataPath": "https://catalog.ourworldindata.org/baked-variables/live_grapher/data/147557.json",
  "metadataPath": "https://catalog.ourworldindata.org/baked-variables/live_grapher/metadata/147557.json",
  "datasetName": "Climate impact on crop yields (Ray et al. 2019)",
  "type": "int",
  "nonRedistributable": false,
  "display": {},
  "source": {
    "id": 18064,
    "name": "Ray et al. (2019). Climate change has likely already affected global food production. PLOS One.",
    "dataPublishedBy": "Ray, D. K., West, P. C., Clark, M., Gerber, J. S., Prishchepov, A. V., & Chatterjee, S. (2019). Climate change has likely already affected global food production. PloS one, 14(5), e0217148.",
    "dataPublisherSource": "",
    "link": "https://journals.plos.org/plosone/article?id=10.1371/journal.pone.0217148",
    "retrievedDate": "",
    "additionalInfo": "Ray et al. (2019) modelled the impact of observed climate change on yields of the top ten global crops. These ten crops account for ~83% of global kilocalorie production.\n\nThe impact of climate change on crop yields is calculated as the difference between actual observed yields under current climate conditions and the yields that would have been achieved until historical climate conditions.\n\nHistorical climate is defined as the 30-year average weather prior to 1974. Current climate is defined as the historical climate plus the addition of the linear trend of the weather for the 35 years ending in 2008, from the year 1974."
  },
  "dimensions": {
    "years": {
      "values": [
        {
          "id": 2013
        }
      ]
    },
    "entities": {
      "values": [
        {
          "id": 3,
          "name": "France",
          "code": "FRA"
        },
        {
          "id": 4,
          "name": "Belgium",
          "code": "BEL"
        },
        {
          "id": 6,
          "name": "Germany",
          "code": "DEU"
        },
        {
          "id": 7,
          "name": "Switzerland",
          "code": "CHE"
        },
        {
          "id": 8,
          "name": "Italy",
          "code": "ITA"
        },
        {
          "id": 9,
          "name": "Spain",
          "code": "ESP"
        },
        {
          "id": 11,
          "name": "Poland",
          "code": "POL"
        },
        {
          "id": 12,
          "name": "Russia",
          "code": "RUS"
        },
        {
          "id": 13,
          "name": "United States",
          "code": "USA"
        },
        {
          "id": 14,
          "name": "Japan",
          "code": "JPN"
        },
        {
          "id": 17,
          "name": "Algeria",
          "code": "DZA"
        },
        {
          "id": 19,
          "name": "Angola",
          "code": "AGO"
        },
        {
          "id": 21,
          "name": "Argentina",
          "code": "ARG"
        },
        {
          "id": 23,
          "name": "Australia",
          "code": "AUS"
        },
        {
          "id": 24,
          "name": "Austria",
          "code": "AUT"
        },
        {
          "id": 28,
          "name": "Bangladesh",
          "code": "BGD"
        },
        {
          "id": 31,
          "name": "Belize",
          "code": "BLZ"
        },
        {
          "id": 32,
          "name": "Benin",
          "code": "BEN"
        },
        {
          "id": 33,
          "name": "Bhutan",
          "code": "BTN"
        },
        {
          "id": 36,
          "name": "Botswana",
          "code": "BWA"
        },
        {
          "id": 37,
          "name": "Brazil",
          "code": "BRA"
        },
        {
          "id": 39,
          "name": "Bulgaria",
          "code": "BGR"
        },
        {
          "id": 40,
          "name": "Burkina Faso",
          "code": "BFA"
        },
        {
          "id": 41,
          "name": "Burundi",
          "code": "BDI"
        },
        {
          "id": 42,
          "name": "Cambodia",
          "code": "KHM"
        },
        {
          "id": 43,
          "name": "Cameroon",
          "code": "CMR"
        },
        {
          "id": 44,
          "name": "Canada",
          "code": "CAN"
        },
        {
          "id": 60,
          "name": "Zambia",
          "code": "ZMB"
        },
        {
          "id": 63,
          "name": "Uruguay",
          "code": "URY"
        },
        {
          "id": 64,
          "name": "Tanzania",
          "code": "TZA"
        },
        {
          "id": 65,
          "name": "Egypt",
          "code": "EGY"
        },
        {
          "id": 67,
          "name": "Ukraine",
          "code": "UKR"
        },
        {
          "id": 68,
          "name": "Uganda",
          "code": "UGA"
        },
        {
          "id": 70,
          "name": "Turkey",
          "code": "TUR"
        },
        {
          "id": 74,
          "name": "Togo",
          "code": "TGO"
        },
        {
          "id": 75,
          "name": "Thailand",
          "code": "THA"
        },
        {
          "id": 79,
          "name": "Sudan",
          "code": "SDN"
        },
        {
          "id": 80,
          "name": "Zimbabwe",
          "code": "ZWE"
        },
        {
          "id": 81,
          "name": "South Africa",
          "code": "ZAF"
        },
        {
          "id": 84,
          "name": "Vietnam",
          "code": "VNM"
        },
        {
          "id": 85,
          "name": "Slovakia",
          "code": "SVK"
        },
        {
          "id": 90,
          "name": "Saudi Arabia",
          "code": "SAU"
        },
        {
          "id": 92,
          "name": "Romania",
          "code": "ROU"
        },
        {
          "id": 94,
          "name": "Guinea-Bissau",
          "code": "GNB"
        },
        {
          "id": 95,
          "name": "Portugal",
          "code": "PRT"
        },
        {
          "id": 96,
          "name": "Philippines",
          "code": "PHL"
        },
        {
          "id": 97,
          "name": "Peru",
          "code": "PER"
        },
        {
          "id": 98,
          "name": "Paraguay",
          "code": "PRY"
        },
        {
          "id": 100,
          "name": "Panama",
          "code": "PAN"
        },
        {
          "id": 101,
          "name": "Pakistan",
          "code": "PAK"
        },
        {
          "id": 103,
          "name": "Nigeria",
          "code": "NGA"
        },
        {
          "id": 104,
          "name": "Niger",
          "code": "NER"
        },
        {
          "id": 105,
          "name": "Nicaragua",
          "code": "NIC"
        },
        {
          "id": 106,
          "name": "New Zealand",
          "code": "NZL"
        },
        {
          "id": 107,
          "name": "Nepal",
          "code": "NPL"
        },
        {
          "id": 109,
          "name": "Mozambique",
          "code": "MOZ"
        },
        {
          "id": 110,
          "name": "Morocco",
          "code": "MAR"
        },
        {
          "id": 113,
          "name": "Mexico",
          "code": "MEX"
        },
        {
          "id": 115,
          "name": "Mali",
          "code": "MLI"
        },
        {
          "id": 116,
          "name": "Malaysia",
          "code": "MYS"
        },
        {
          "id": 117,
          "name": "Malawi",
          "code": "MWI"
        },
        {
          "id": 118,
          "name": "Madagascar",
          "code": "MDG"
        },
        {
          "id": 120,
          "name": "Libya",
          "code": "LBY"
        },
        {
          "id": 123,
          "name": "Lesotho",
          "code": "LSO"
        },
        {
          "id": 124,
          "name": "Lebanon",
          "code": "LBN"
        },
        {
          "id": 125,
          "name": "Laos",
          "code": "LAO"
        },
        {
          "id": 127,
          "name": "South Korea",
          "code": "KOR"
        },
        {
          "id": 132,
          "name": "Jamaica",
          "code": "JAM"
        },
        {
          "id": 135,
          "name": "Iran",
          "code": "IRN"
        },
        {
          "id": 136,
          "name": "Indonesia",
          "code": "IDN"
        },
        {
          "id": 137,
          "name": "India",
          "code": "IND"
        },
        {
          "id": 138,
          "name": "Hungary",
          "code": "HUN"
        },
        {
          "id": 141,
          "name": "Sri Lanka",
          "code": "LKA"
        },
        {
          "id": 142,
          "name": "Myanmar",
          "code": "MMR"
        },
        {
          "id": 143,
          "name": "Cote d'Ivoire",
          "code": "CIV"
        },
        {
          "id": 147,
          "name": "Guinea",
          "code": "GIN"
        },
        {
          "id": 149,
          "name": "Greece",
          "code": "GRC"
        },
        {
          "id": 150,
          "name": "Ghana",
          "code": "GHA"
        },
        {
          "id": 151,
          "name": "Gambia",
          "code": "GMB"
        },
        {
          "id": 160,
          "name": "Dominican Republic",
          "code": "DOM"
        },
        {
          "id": 162,
          "name": "Czechia",
          "code": "CZE"
        },
        {
          "id": 164,
          "name": "Cuba",
          "code": "CUB"
        },
        {
          "id": 167,
          "name": "Democratic Republic of Congo",
          "code": "COD"
        },
        {
          "id": 170,
          "name": "Colombia",
          "code": "COL"
        },
        {
          "id": 171,
          "name": "China",
          "code": "CHN"
        },
        {
          "id": 172,
          "name": "Chile",
          "code": "CHL"
        },
        {
          "id": 174,
          "name": "Central African Republic",
          "code": "CAF"
        },
        {
          "id": 198,
          "name": "Taiwan",
          "code": "TWN"
        },
        {
          "id": 201,
          "name": "Ecuador",
          "code": "ECU"
        },
        {
          "id": 208,
          "name": "Kuwait",
          "code": "KWT"
        },
        {
          "id": 238,
          "name": "Venezuela",
          "code": "VEN"
        },
        {
          "id": 259,
          "name": "El Salvador",
          "code": "SLV"
        },
        {
          "id": 277,
          "name": "Oceania",
          "code": null
        },
        {
          "id": 289,
          "name": "Sub-Saharan Africa",
          "code": null
        },
        {
          "id": 355,
          "name": "World",
          "code": "OWID_WRL"
        },
        {
          "id": 464,
          "name": "Northern Africa",
          "code": null
        },
        {
          "id": 10892,
          "name": "North and Central America",
          "code": null
        },
        {
          "id": 54352,
          "name": "Bolivia (Plurinational State of)",
          "code": null
        },
        {
          "id": 217701,
          "name": "Caribbean and South America",
          "code": null
        },
        {
          "id": 217702,
          "name": "Western and Southern Europe",
          "code": null
        },
        {
          "id": 217703,
          "name": "Eastern and Northern Europe",
          "code": null
        },
        {
          "id": 217704,
          "name": "Central and Eastern Asia",
          "code": null
        },
        {
          "id": 217705,
          "name": "Western, Southern and South-east Asia",
          "code": null
        }
      ]
    }
  }
}