{
  "id": 147400,
  "name": "below 2$ a day",
  "unit": "",
  "createdAt": "2021-06-23T12:48:30.000Z",
  "updatedAt": "2023-06-15T05:05:42.000Z",
  "coverage": "",
  "timespan": "",
  "datasetId": 5333,
  "columnOrder": 0,
  "dataPath": "https://api.ourworldindata.org/v1/indicators/147400.data.json",
  "metadataPath": "https://api.ourworldindata.org/v1/indicators/147400.metadata.json",
  "datasetName": "Historical estimates of number of people living at different income thresholds globally (OWID based on Maddison Project Database 2020, GCIP and van Zanden et al. (2014))",
  "type": "float",
  "nonRedistributable": false,
  "display": {
    "includeInTable": true
  },
  "source": {
    "id": 18053,
    "name": "OWID based on Maddison Project Database 2020, GCIP and van Zanden et al. (2014))",
    "dataPublishedBy": "OWID based on Maddison Project Database 2020, GCIP and van Zanden et al. (2014))",
    "dataPublisherSource": "",
    "link": "",
    "retrievedDate": "",
    "additionalInfo": "See data appendix: "
  },
  "dimensions": {
    "years": {
      "values": [
        {
          "id": 1820
        },
        {
          "id": 1850
        },
        {
          "id": 1870
        },
        {
          "id": 1890
        },
        {
          "id": 1910
        },
        {
          "id": 1929
        },
        {
          "id": 1950
        },
        {
          "id": 1960
        },
        {
          "id": 1970
        },
        {
          "id": 1980
        },
        {
          "id": 1990
        },
        {
          "id": 2000
        },
        {
          "id": 2005
        },
        {
          "id": 2010
        },
        {
          "id": 2017
        }
      ]
    },
    "entities": {
      "values": [
        {
          "id": 355,
          "name": "World",
          "code": "OWID_WRL"
        }
      ]
    }
  }
}